cosmolog/__init__.py
cosmolog/cosmologger.py
cosmolog/bin/__init__.py
cosmolog/bin/cli.py
cosmolog-0.9.12.dist-info/AUTHORS
cosmolog-0.9.12.dist-info/LICENSE
cosmolog-0.9.12.dist-info/METADATA
cosmolog-0.9.12.dist-info/WHEEL
cosmolog-0.9.12.dist-info/entry_points.txt
cosmolog-0.9.12.dist-info/top_level.txt
cosmolog-0.9.12.dist-info/RECORD
