Metadata-Version: 2.1
Name: cosmolog
Version: 0.9.12
Summary: cosmolog: structured python logger
Author-email: Isil Demir <isil@planet.com>
Classifier: Development Status :: 5 - Production/Stable
Classifier: Environment :: Console
Classifier: Operating System :: OS Independent
Classifier: Programming Language :: Python
Classifier: Programming Language :: Python :: 3
Requires-Python: >=3.6
License-File: LICENSE
License-File: AUTHORS
Requires-Dist: click >=6.3
Requires-Dist: pytz >=2015.7
Requires-Dist: python-dateutil >=2.4.2
Requires-Dist: importlib-metadata ; python_version < "3.8"
Provides-Extra: test
Requires-Dist: pytest >=3.0.2 ; extra == 'test'
Requires-Dist: flake8 ==3.2.0 ; extra == 'test'
Requires-Dist: freezegun ==1.2.1 ; extra == 'test'
Requires-Dist: tox ==2.9.1 ; extra == 'test'
